pyapitest/__init__.py
pyapitest-0.0.1.dev4.dist-info/DESCRIPTION.rst
pyapitest-0.0.1.dev4.dist-info/METADATA
pyapitest-0.0.1.dev4.dist-info/RECORD
pyapitest-0.0.1.dev4.dist-info/WHEEL
pyapitest-0.0.1.dev4.dist-info/metadata.json
pyapitest-0.0.1.dev4.dist-info/top_level.txt
