Metadata-Version: 2.0
Name: pyapitest
Version: 0.0.1.dev4
Summary: Simple API testing in Python
Home-page: https://github.com/danielatdattrixdotcom/pyapitest
Author: Daniel Anderson
Author-email: daniel@dattrix.com
License: BSD
Keywords: api testing json
Platform: UNKNOWN
Classifier: Development Status :: 3 - Alpha
Classifier: Intended Audience :: Developers
Classifier: Topic :: Software Development :: Testing
Classifier: License :: OSI Approved :: BSD License
Classifier: Programming Language :: Python :: 2
Classifier: Programming Language :: Python :: 2.7
Classifier: Programming Language :: Python :: 3
Requires-Dist: requests
Requires-Dist: cerberus
Requires-Dist: six
